apigee_python/__init__.py
apigee_python/v1/__init__.py
apigee_python/v1/exceptions.py
apigee_python/v1/organizations/__init__.py
apigee_python/v1/organizations/apigee.py
apigee_python/v1/organizations/products.py
apigee_python/v1/organizations/proxies.py
apigee_python/v1/organizations/resourcefiles.py
apigee_python/v1/organizations/rest.py
apigee_python/v1/organizations/roles.py
apigee_python-0.0.6.dist-info/LICENSE
apigee_python-0.0.6.dist-info/METADATA
apigee_python-0.0.6.dist-info/WHEEL
apigee_python-0.0.6.dist-info/top_level.txt
apigee_python-0.0.6.dist-info/RECORD
